algefunc/__init__.py
algefunc/algefunc.py
algefunc-0.1.0.dist-info/LICENSE
algefunc-0.1.0.dist-info/METADATA
algefunc-0.1.0.dist-info/WHEEL
algefunc-0.1.0.dist-info/top_level.txt
algefunc-0.1.0.dist-info/RECORD
